p3d_flatpak/__init__.py
p3d_flatpak/p3d_flatpak.py
panda3d_flatpak-0.1.2.dist-info/LICENSE
panda3d_flatpak-0.1.2.dist-info/METADATA
panda3d_flatpak-0.1.2.dist-info/WHEEL
panda3d_flatpak-0.1.2.dist-info/top_level.txt
panda3d_flatpak-0.1.2.dist-info/RECORD
