Metadata-Version: 2.1
Name: panda3d-flatpak
Version: 0.1.2
Summary: Flatpak support for Panda3D
Home-page: https://www.ya2.it/pages/panda3d-flatpak.html
Author: Flavio Calva
Author-email: f.calva@gmail.com
License: UNKNOWN
Project-URL: Repository, https://git.ya2.it/?p=panda3d-flatpak.git
Platform: UNKNOWN
Classifier: Programming Language :: Python :: 3
Classifier: License :: OSI Approved :: BSD License
Classifier: Operating System :: POSIX :: Linux
Requires-Python: >=3.8
License-File: LICENSE
